pycups_po/__init__.py
pycups_po/__main__.py
pycups_po/generator.py
pycups_po/helpers.py
pycups_po/models/__init__.py
pycups_po/models/options.py
pycups_po-0.1.1.dist-info/LICENSE
pycups_po-0.1.1.dist-info/METADATA
pycups_po-0.1.1.dist-info/WHEEL
pycups_po-0.1.1.dist-info/entry_points.txt
pycups_po-0.1.1.dist-info/top_level.txt
pycups_po-0.1.1.dist-info/RECORD
