Metadata-Version: 2.1
Name: pycups-po
Version: 0.1.1
Summary: CUPS print options generator from PPD
Home-page: https://github.com/WhiteApfel/pycups_po
Author: WhiteApfel
Author-email: white@pfel.ru
License: Mozilla Public License 2.0
Project-URL: Source code, https://github.com/WhiteApfel/pycups_po
Project-URL: Write me, https://t.me/whiteapfel
Keywords: pycups cups ppd options
License-File: LICENSE
Requires-Dist: pycups (==2.0.1)
Requires-Dist: pytest (~=7.1.3)
Requires-Dist: setuptools (~=65.4.1)
Requires-Dist: typer (~=0.6.1)
